FileCrypt/__init__.py
filecrypt-1.0.4.dist-info/LICENSE
filecrypt-1.0.4.dist-info/METADATA
filecrypt-1.0.4.dist-info/WHEEL
filecrypt-1.0.4.dist-info/top_level.txt
filecrypt-1.0.4.dist-info/RECORD
