Metadata-Version: 2.1
Name: filecrypt
Version: 1.0.4
Summary: Wrapper for FileCrypt.cc
Home-page: https://github.com/TA40/FileCryptcc
Author: Tami
Author-email: tammyshead@tuta.io
License: UNKNOWN
Platform: UNKNOWN
Classifier: Programming Language :: Python :: 3
Classifier: License :: OSI Approved :: MIT License
Classifier: Operating System :: OS Independent
